<?xml version="1.0" encoding="UTF-8"?>
<compendium version="5" auto_indent="NO">
    <monster>
        <name>HelmutVanHeuten</name>
        <size>M</size>
        <type>humanoid (human)</type>
        <alignment>lawful good</alignment>
        <ac>10</ac>
        <hp>1</hp>
        <speed>30 ft.</speed>
        <str>10</str>
        <dex>10</dex>
        <con>10</con>
        <int>10</int>
        <wis>10</wis>
        <cha>10</cha>
        <cr>1</cr>
        <description>Helmut Van Heuten is a wealthy and respected merchant, in his sixties, with a well-groomed white beard and fine but unpretentious clothing. He always wears a ring with the symbol of Tyr — a set of scales — and has the habit of offering hot tea to anyone who sits in his study. He has scribe's hands, not a warrior's, and a calm, gentle voice that inspires trust.
He is courteous, methodical, and genuinely devout. He is not an adventurer and doesn't pretend to be — he knows his role is to provide resources, not to wield swords.
Role: secondary</description>
    </monster>
</compendium>